{
    "place":[
{"id":1,"x":233,"y":205,"label":"1号館","info":["aa"]},
{"id":2,"x":203,"y":132,"label":"1号館別館","info":["aa"]},
{"id":3,"x":349,"y":210,"label":"2号館実験棟","info":["aa"]},
{"id":4,"x":432,"y":250,"label":"新2号館","info":["aa"]},
{"id":5,"x":505,"y":237,"label":"3号館","info":["aa"]},
{"id":6,"x":500,"y":264,"label":"3号館別館","info":["aa"]},
{"id":7,"x":525,"y":255,"label":"バイオ環境化学実験棟","info":["aa"]},
{"id":8,"x":511,"y":151,"label":"4号館","info":["aa"]},
{"id":9,"x":543,"y":117,"label":"4号館別館","info":["aa"]},
{"id":10,"x":432,"y":174,"label":"5号館講義実験棟","info":["aa"]},
{"id":11,"x":554,"y":194,"label":"6号館","info":["aa"]},
{"id":12,"x":321,"y":151,"label":"7号館","info":["aa"]},
{"id":13,"x":459,"y":206,"label":"8号館","info":["aa"]},
{"id":14,"x":245,"y":133,"label":"9号館","info":["aa"]},
{"id":15,"x":186,"y":190,"label":"10号館","info":["aa"]},
{"id":16,"x":222,"y":172,"label":"10号館・旧1号館","info":["aa"]},
{"id":17,"x":573,"y":119,"label":"11号館","info":["aa"]},
{"id":18,"x":387,"y":251,"label":"12号館","info":["aa"]},
{"id":19,"x":563,"y":165,"label":"13号館","info":["aa"]},
{"id":20,"x":337,"y":256,"label":"図書館","info":["aa"]},
{"id":21,"x":460,"y":166,"label":"計算センター","info":["aa"]},
{"id":22,"x":495,"y":174,"label":"情報教育センター","info":["aa"]},
{"id":23,"x":473,"y":313,"label":"総合技術研究所","info":["aa"]},
{"id":24,"x":219,"y":95,"label":"耐震実験センター","info":["aa"]},
{"id":25,"x":368,"y":121,"label":"振動実験棟","info":["aa"]},
{"id":26,"x":165,"y":133,"label":" 地域防災研究センター","info":["aa"]},
{"id":27,"x":280,"y":123,"label":"エコ電力研究センター","info":["aa"]},
{"id":28,"x":273,"y":297,"label":"本部棟","info":["aa"]},
{"id":29,"x":258,"y":251,"label":"第1本部棟","info":["aa"]},
{"id":30,"x":300,"y":259,"label":"第2本部棟","info":["aa"]},
{"id":31,"x":305,"y":191,"label":"愛和会館","info":["aa"]},
{"id":32,"x":262,"y":184,"label":"AITプラザ","info":["aa"]},
{"id":33,"x":428,"y":207,"label":"セントラルテラス","info":["aa"]},
{"id":34,"x":395,"y":404,"label":"鉀徳館（講堂兼体育館）","info":["aa"]},
{"id":35,"x":686,"y":318,"label":"総合運動場管理棟","info":["aa"]},
{"id":36,"x":346,"y":481,"label":"小体育館","info":["aa"]},
{"id":37,"x":247,"y":103,"label":"第3クラブハウス","info":["aa"]},
{"id":38,"x":464,"y":368,"label":"第4クラブハウス","info":["aa"]},
{"id":39,"x":688,"y":495,"label":"第5クラブハウス","info":["aa"]},
{"id":40,"x":331,"y":271,"label":"庭球場管理ハウス","info":["aa"]}
    ]
}
